{
  "name": "net/minecraft/client/resources/ClientPackSource",
  "methods": [
    {
      "name": "checkHash",
      "descriptor": "(Ljava/lang/String;Ljava/io/File;)Z",
      "parameters": [
        {
          "index": 1,
          "name": "expectedHash"
        },
        {
          "index": 2,
          "name": "file"
        }
      ]
    },
    {
      "name": "deleteQuietly",
      "descriptor": "(Ljava/io/File;)V",
      "parameters": [
        {
          "index": 0,
          "name": "file"
        }
      ]
    },
    {
      "name": "loadPacks",
      "descriptor": "(Ljava/util/function/Consumer;Lnet/minecraft/server/packs/repository/Pack$PackConstructor;)V",
      "parameters": [
        {
          "index": 1,
          "name": "infoConsumer"
        },
        {
          "index": 2,
          "name": "infoFactory"
        }
      ]
    },
    {
      "name": "setServerPack",
      "descriptor": "(Ljava/io/File;Lnet/minecraft/server/packs/repository/PackSource;)Ljava/util/concurrent/CompletableFuture;",
      "parameters": [
        {
          "index": 1,
          "name": "file"
        }
      ]
    }
  ]
}