{
  "name": "ack",
  "fields": [
    {
      "name": "a",
      "descriptor": "Los;"
    },
    {
      "name": "b",
      "descriptor": "Lnet/minecraft/server/MinecraftServer;"
    },
    {
      "name": "c",
      "descriptor": "Loe;"
    }
  ],
  "methods": [
    {
      "name": "<clinit>",
      "descriptor": "()V"
    },
    {
      "name": "<init>",
      "descriptor": "(Lnet/minecraft/server/MinecraftServer;Loe;)V"
    },
    {
      "name": "a",
      "descriptor": "()Loe;",
      "javadoc": [
        "Returns this the NetworkManager instance registered with this NetworkHandlerPlayClient"
      ]
    },
    {
      "name": "a",
      "descriptor": "(Los;)V",
      "javadoc": [
        "Invoked when disconnecting, the parameter is a ChatComponent describing the reason for termination"
      ],
      "parameters": [
        {
          "index": 1,
          "name": "pReason"
        }
      ]
    },
    {
      "name": "a",
      "descriptor": "(Lvi;)V",
      "javadoc": [
        "There are two recognized intentions for initiating a handshake: logging in and acquiring server status. The NetworkManager's protocol will be reconfigured according to the specified intention, although a login-intention must pass a versioncheck or receive a disconnect otherwise"
      ],
      "parameters": [
        {
          "index": 1,
          "name": "pPacket"
        }
      ]
    }
  ]
}