{
  "name": "afo",
  "fields": [
    {
      "name": "A",
      "descriptor": "Lww;"
    },
    {
      "name": "B",
      "descriptor": "Lww;"
    },
    {
      "name": "C",
      "descriptor": "Lww;"
    },
    {
      "name": "D",
      "descriptor": "Lww;"
    },
    {
      "name": "E",
      "descriptor": "Lww;"
    },
    {
      "name": "F",
      "descriptor": "Lww;"
    },
    {
      "name": "G",
      "descriptor": "Lww;"
    },
    {
      "name": "H",
      "descriptor": "Lww;"
    },
    {
      "name": "I",
      "descriptor": "Lww;"
    },
    {
      "name": "J",
      "descriptor": "Lww;"
    },
    {
      "name": "K",
      "descriptor": "Lww;"
    },
    {
      "name": "L",
      "descriptor": "Lww;"
    },
    {
      "name": "M",
      "descriptor": "Lww;"
    },
    {
      "name": "N",
      "descriptor": "Lww;"
    },
    {
      "name": "O",
      "descriptor": "Lww;"
    },
    {
      "name": "P",
      "descriptor": "Lww;"
    },
    {
      "name": "Q",
      "descriptor": "Lww;"
    },
    {
      "name": "R",
      "descriptor": "Lww;"
    },
    {
      "name": "S",
      "descriptor": "Lww;"
    },
    {
      "name": "T",
      "descriptor": "Lww;"
    },
    {
      "name": "U",
      "descriptor": "Lww;"
    },
    {
      "name": "V",
      "descriptor": "Lww;"
    },
    {
      "name": "W",
      "descriptor": "Lww;"
    },
    {
      "name": "X",
      "descriptor": "Lww;"
    },
    {
      "name": "Y",
      "descriptor": "Lww;"
    },
    {
      "name": "Z",
      "descriptor": "Lww;"
    },
    {
      "name": "a",
      "descriptor": "Lafn;"
    },
    {
      "name": "aA",
      "descriptor": "Lww;"
    },
    {
      "name": "aB",
      "descriptor": "Lww;"
    },
    {
      "name": "aC",
      "descriptor": "Lww;"
    },
    {
      "name": "aD",
      "descriptor": "Lww;"
    },
    {
      "name": "aE",
      "descriptor": "Lww;"
    },
    {
      "name": "aF",
      "descriptor": "Lww;"
    },
    {
      "name": "aa",
      "descriptor": "Lww;"
    },
    {
      "name": "ab",
      "descriptor": "Lww;"
    },
    {
      "name": "ac",
      "descriptor": "Lww;"
    },
    {
      "name": "ad",
      "descriptor": "Lww;"
    },
    {
      "name": "ae",
      "descriptor": "Lww;"
    },
    {
      "name": "af",
      "descriptor": "Lww;"
    },
    {
      "name": "ag",
      "descriptor": "Lww;"
    },
    {
      "name": "ah",
      "descriptor": "Lww;"
    },
    {
      "name": "ai",
      "descriptor": "Lww;"
    },
    {
      "name": "aj",
      "descriptor": "Lww;"
    },
    {
      "name": "ak",
      "descriptor": "Lww;"
    },
    {
      "name": "al",
      "descriptor": "Lww;"
    },
    {
      "name": "am",
      "descriptor": "Lww;"
    },
    {
      "name": "an",
      "descriptor": "Lww;"
    },
    {
      "name": "ao",
      "descriptor": "Lww;"
    },
    {
      "name": "ap",
      "descriptor": "Lww;"
    },
    {
      "name": "aq",
      "descriptor": "Lww;"
    },
    {
      "name": "ar",
      "descriptor": "Lww;"
    },
    {
      "name": "as",
      "descriptor": "Lww;"
    },
    {
      "name": "at",
      "descriptor": "Lww;"
    },
    {
      "name": "au",
      "descriptor": "Lww;"
    },
    {
      "name": "av",
      "descriptor": "Lww;"
    },
    {
      "name": "aw",
      "descriptor": "Lww;"
    },
    {
      "name": "ax",
      "descriptor": "Lww;"
    },
    {
      "name": "ay",
      "descriptor": "Lww;"
    },
    {
      "name": "az",
      "descriptor": "Lww;"
    },
    {
      "name": "b",
      "descriptor": "Lafn;"
    },
    {
      "name": "c",
      "descriptor": "Lafn;"
    },
    {
      "name": "d",
      "descriptor": "Lafn;"
    },
    {
      "name": "e",
      "descriptor": "Lafn;"
    },
    {
      "name": "f",
      "descriptor": "Lafn;"
    },
    {
      "name": "g",
      "descriptor": "Lafn;"
    },
    {
      "name": "h",
      "descriptor": "Lafn;"
    },
    {
      "name": "i",
      "descriptor": "Lafn;"
    },
    {
      "name": "j",
      "descriptor": "Lww;"
    },
    {
      "name": "k",
      "descriptor": "Lww;"
    },
    {
      "name": "l",
      "descriptor": "Lww;"
    },
    {
      "name": "m",
      "descriptor": "Lww;"
    },
    {
      "name": "n",
      "descriptor": "Lww;"
    },
    {
      "name": "o",
      "descriptor": "Lww;"
    },
    {
      "name": "p",
      "descriptor": "Lww;"
    },
    {
      "name": "q",
      "descriptor": "Lww;"
    },
    {
      "name": "r",
      "descriptor": "Lww;"
    },
    {
      "name": "s",
      "descriptor": "Lww;"
    },
    {
      "name": "t",
      "descriptor": "Lww;"
    },
    {
      "name": "u",
      "descriptor": "Lww;"
    },
    {
      "name": "v",
      "descriptor": "Lww;"
    },
    {
      "name": "w",
      "descriptor": "Lww;"
    },
    {
      "name": "x",
      "descriptor": "Lww;"
    },
    {
      "name": "y",
      "descriptor": "Lww;"
    },
    {
      "name": "z",
      "descriptor": "Lww;"
    }
  ],
  "methods": [
    {
      "name": "<clinit>",
      "descriptor": "()V"
    },
    {
      "name": "<init>",
      "descriptor": "()V"
    },
    {
      "name": "a",
      "descriptor": "(Ljava/lang/String;Lafm;)Lww;",
      "parameters": [
        {
          "index": 0,
          "name": "pKey"
        },
        {
          "index": 1,
          "name": "pFormatter"
        }
      ]
    },
    {
      "name": "a",
      "descriptor": "(Ljava/lang/String;Lgw;)Lafn;",
      "parameters": [
        {
          "index": 0,
          "name": "pKey"
        },
        {
          "index": 1,
          "name": "pRegistry"
        }
      ]
    }
  ]
}