{
  "name": "age",
  "fields": [
    {
      "name": "a",
      "descriptor": "Lorg/apache/logging/log4j/Logger;"
    },
    {
      "name": "b",
      "descriptor": "Lgx;"
    },
    {
      "name": "c",
      "descriptor": "Lagc;"
    }
  ],
  "methods": [
    {
      "name": "<clinit>",
      "descriptor": "()V"
    },
    {
      "name": "<init>",
      "descriptor": "(Lgx;)V"
    },
    {
      "name": "a",
      "descriptor": "()Lagc;"
    },
    {
      "name": "a",
      "descriptor": "(I)[Ljava/util/concurrent/CompletableFuture;"
    },
    {
      "name": "a",
      "descriptor": "(Lado$a;Ladt;Lapu;Lapu;Ljava/util/concurrent/Executor;Ljava/util/concurrent/Executor;)Ljava/util/concurrent/CompletableFuture;"
    },
    {
      "name": "a",
      "descriptor": "(Ladt;Ljava/util/concurrent/Executor;Lafy;)Lage$a;"
    },
    {
      "name": "a",
      "descriptor": "(Ladt;Ljava/util/concurrent/Executor;Ljava/util/List;Lafy;)V"
    },
    {
      "name": "a",
      "descriptor": "(Lagc$a;Lage$a;)V"
    },
    {
      "name": "a",
      "descriptor": "(Lagd;Ladt;)Lagb;"
    },
    {
      "name": "a",
      "descriptor": "(Lage$a;)Ljava/util/concurrent/CompletableFuture;"
    },
    {
      "name": "a",
      "descriptor": "(Ljava/util/List;Ljava/lang/Void;)V"
    },
    {
      "name": "a",
      "descriptor": "(Ljava/util/Map$Entry;)Ljava/lang/String;"
    }
  ]
}