{
  "name": "amn",
  "methods": [
    {
      "name": "<init>",
      "descriptor": "(Ljava/lang/String;Lcom/mojang/datafixers/schemas/Schema;Z)V"
    },
    {
      "name": "a",
      "descriptor": "(Ljava/lang/String;Lcom/mojang/datafixers/Typed;)Lcom/mojang/datafixers/util/Pair;"
    },
    {
      "name": "a",
      "descriptor": "(Ljava/lang/String;Lcom/mojang/serialization/Dynamic;)Lcom/mojang/datafixers/util/Pair;",
      "parameters": [
        {
          "index": 1,
          "name": "name"
        },
        {
          "index": 2,
          "name": "tag"
        }
      ]
    }
  ]
}