{
  "name": "arf$b",
  "fields": [
    {
      "name": "a",
      "descriptor": "Ljava/util/Collection;"
    },
    {
      "name": "b",
      "descriptor": "Ljava/util/Collection;"
    },
    {
      "name": "c",
      "descriptor": "Lcom/mojang/serialization/Codec;"
    }
  ],
  "methods": [
    {
      "name": "<init>",
      "descriptor": "(Ljava/util/Collection;Ljava/util/Collection;)V"
    },
    {
      "name": "<init>",
      "descriptor": "(Ljava/util/Collection;Ljava/util/Collection;Larf$1;)V"
    },
    {
      "name": "a",
      "descriptor": "()Larf;"
    },
    {
      "name": "a",
      "descriptor": "(Lcom/mojang/serialization/Dynamic;)Larf;",
      "parameters": [
        {
          "index": 1,
          "name": "pOps"
        }
      ]
    },
    {
      "name": "b",
      "descriptor": "()Lcom/mojang/serialization/Codec;"
    }
  ]
}