{
  "name": "asx",
  "fields": [
    {
      "name": "a",
      "descriptor": "Ljava/util/Map;"
    },
    {
      "name": "b",
      "descriptor": "Lasy;"
    },
    {
      "name": "c",
      "descriptor": "I"
    },
    {
      "name": "d",
      "descriptor": "Ljava/lang/String;"
    }
  ],
  "methods": [
    {
      "name": "<init>",
      "descriptor": "(Lasy;I)V"
    },
    {
      "name": "a",
      "descriptor": "()Z"
    },
    {
      "name": "a",
      "descriptor": "(I)Lasx;"
    },
    {
      "name": "a",
      "descriptor": "(II)Z"
    },
    {
      "name": "a",
      "descriptor": "(ILaus;)D"
    },
    {
      "name": "a",
      "descriptor": "(Lasx;)I"
    },
    {
      "name": "a",
      "descriptor": "(Latf;Latf;Latt;ID)V"
    },
    {
      "name": "a",
      "descriptor": "(Latt;I)V"
    },
    {
      "name": "a",
      "descriptor": "(Latt;Laur;I)V"
    },
    {
      "name": "a",
      "descriptor": "(Laup;Ljava/lang/String;DLaus$a;)Lasx;"
    },
    {
      "name": "b",
      "descriptor": "()Ljava/lang/String;"
    },
    {
      "name": "b",
      "descriptor": "(Latt;Laur;I)V"
    },
    {
      "name": "c",
      "descriptor": "()Ljava/lang/String;"
    },
    {
      "name": "d",
      "descriptor": "()Los;"
    },
    {
      "name": "e",
      "descriptor": "()Lasy;"
    },
    {
      "name": "f",
      "descriptor": "()I"
    },
    {
      "name": "g",
      "descriptor": "()Ljava/util/Map;"
    },
    {
      "name": "h",
      "descriptor": "()Z"
    }
  ]
}