{
  "name": "av",
  "fields": [
    {
      "name": "a",
      "descriptor": "Lav;"
    },
    {
      "name": "b",
      "descriptor": "Lbz$c;"
    },
    {
      "name": "c",
      "descriptor": "Lbz$c;"
    },
    {
      "name": "d",
      "descriptor": "Lbg;"
    },
    {
      "name": "e",
      "descriptor": "Ljava/lang/Boolean;"
    },
    {
      "name": "f",
      "descriptor": "Law;"
    }
  ],
  "methods": [
    {
      "name": "<clinit>",
      "descriptor": "()V"
    },
    {
      "name": "<init>",
      "descriptor": "()V"
    },
    {
      "name": "<init>",
      "descriptor": "(Lbz$c;Lbz$c;Lbg;Ljava/lang/Boolean;Law;)V"
    },
    {
      "name": "a",
      "descriptor": "()Lcom/google/gson/JsonElement;"
    },
    {
      "name": "a",
      "descriptor": "(Laah;Lapk;FFZ)Z"
    },
    {
      "name": "a",
      "descriptor": "(Lcom/google/gson/JsonElement;)Lav;"
    }
  ]
}