{
  "name": "bsv$b",
  "fields": [
    {
      "name": "a",
      "descriptor": "Lbsv$b;"
    },
    {
      "name": "b",
      "descriptor": "Lbsv$b;"
    },
    {
      "name": "c",
      "descriptor": "Lbsv$b;"
    },
    {
      "name": "d",
      "descriptor": "Lbsv$b;"
    },
    {
      "name": "e",
      "descriptor": "Lbsv$b;"
    },
    {
      "name": "f",
      "descriptor": "Lbsv$b;"
    },
    {
      "name": "g",
      "descriptor": "Lbsv$b;"
    },
    {
      "name": "h",
      "descriptor": "Lbsv$b;"
    },
    {
      "name": "i",
      "descriptor": "Lbsv$b;"
    },
    {
      "name": "j",
      "descriptor": "Lbsv$b;"
    },
    {
      "name": "k",
      "descriptor": "Lbsv$b;"
    },
    {
      "name": "l",
      "descriptor": "Lbsv$b;"
    },
    {
      "name": "m",
      "descriptor": "Lbsv$b;"
    },
    {
      "name": "n",
      "descriptor": "Lbsv$b;"
    },
    {
      "name": "o",
      "descriptor": "Lbsv$b;"
    },
    {
      "name": "p",
      "descriptor": "Lbsv$b;"
    },
    {
      "name": "q",
      "descriptor": "Lbsv$b;"
    },
    {
      "name": "r",
      "descriptor": "Lcom/mojang/serialization/Codec;"
    },
    {
      "name": "s",
      "descriptor": "Ljava/util/Map;"
    },
    {
      "name": "t",
      "descriptor": "Ljava/lang/String;"
    },
    {
      "name": "u",
      "descriptor": "[Lbsv$b;"
    }
  ],
  "methods": [
    {
      "name": "<clinit>",
      "descriptor": "()V"
    },
    {
      "name": "<init>",
      "descriptor": "(Ljava/lang/String;ILjava/lang/String;)V"
    },
    {
      "name": "a",
      "descriptor": "()Ljava/lang/String;"
    },
    {
      "name": "a",
      "descriptor": "(Lbsv$b;)Lbsv$b;"
    },
    {
      "name": "a",
      "descriptor": "(Ljava/lang/String;)Lbsv$b;"
    },
    {
      "name": "b",
      "descriptor": "()Ljava/lang/String;"
    },
    {
      "name": "valueOf",
      "descriptor": "(Ljava/lang/String;)Lbsv$b;"
    },
    {
      "name": "values",
      "descriptor": "()[Lbsv$b;"
    }
  ]
}