{
  "name": "dfe",
  "fields": [
    {
      "name": "a",
      "descriptor": "Ldfe$a;"
    },
    {
      "name": "b",
      "descriptor": "Ljava/lang/String;"
    },
    {
      "name": "c",
      "descriptor": "I"
    },
    {
      "name": "d",
      "descriptor": "I"
    }
  ],
  "methods": [
    {
      "name": "<init>",
      "descriptor": "(Ldfe$a;ILjava/lang/String;)V"
    },
    {
      "name": "a",
      "descriptor": "()V"
    },
    {
      "name": "a",
      "descriptor": "(Ldfd;)V",
      "parameters": [
        {
          "index": 1,
          "name": "pManager"
        }
      ]
    },
    {
      "name": "a",
      "descriptor": "(Ldfe$a;Ljava/lang/String;Ljava/io/InputStream;Ljava/lang/String;)Ldfe;"
    },
    {
      "name": "b",
      "descriptor": "()Ljava/lang/String;"
    }
  ]
}