{
  "name": "dni",
  "fields": [
    {
      "name": "a",
      "descriptor": "Lorg/apache/logging/log4j/Logger;"
    },
    {
      "name": "b",
      "descriptor": "Lach;"
    },
    {
      "name": "c",
      "descriptor": "[B"
    },
    {
      "name": "d",
      "descriptor": "Ljava/lang/String;"
    },
    {
      "name": "e",
      "descriptor": "Ljava/util/Map;"
    }
  ],
  "methods": [
    {
      "name": "<clinit>",
      "descriptor": "()V"
    },
    {
      "name": "<init>",
      "descriptor": "(Lach;[BLjava/lang/String;)V"
    },
    {
      "name": "a",
      "descriptor": "()Lit/unimi/dsi/fastutil/ints/IntSet;"
    },
    {
      "name": "a",
      "descriptor": "(B)I"
    },
    {
      "name": "a",
      "descriptor": "(I)Ldec;"
    },
    {
      "name": "a",
      "descriptor": "(Lvk;)Ldet;"
    },
    {
      "name": "b",
      "descriptor": "()Lorg/apache/logging/log4j/Logger;"
    },
    {
      "name": "b",
      "descriptor": "(B)I"
    },
    {
      "name": "b",
      "descriptor": "(I)Lvk;"
    },
    {
      "name": "close",
      "descriptor": "()V"
    }
  ]
}