{
  "name": "dvc",
  "fields": [
    {
      "name": "A",
      "descriptor": "Ldwn;"
    },
    {
      "name": "B",
      "descriptor": "Ldwn;"
    },
    {
      "name": "a",
      "descriptor": "Ldwn;"
    },
    {
      "name": "b",
      "descriptor": "Ldwn;"
    },
    {
      "name": "y",
      "descriptor": "Ldwn;"
    },
    {
      "name": "z",
      "descriptor": "Ldwn;"
    }
  ],
  "methods": [
    {
      "name": "<init>",
      "descriptor": "(FII)V"
    },
    {
      "name": "a",
      "descriptor": "(Laqa;FFFFF)V",
      "javadoc": [
        "Sets this entity's model rotation angles"
      ],
      "parameters": [
        {
          "index": 1,
          "name": "pEntityIn"
        },
        {
          "index": 2,
          "name": "pLimbSwing"
        },
        {
          "index": 3,
          "name": "pLimbSwingAmount"
        },
        {
          "index": 4,
          "name": "pAgeInTicks"
        },
        {
          "index": 5,
          "name": "pNetHeadYaw"
        },
        {
          "index": 6,
          "name": "pHeadPitch"
        }
      ]
    },
    {
      "name": "a",
      "descriptor": "(Laqm;F)V"
    },
    {
      "name": "a",
      "descriptor": "(Laqm;FFFFF)V",
      "javadoc": [
        "Sets this entity's model rotation angles"
      ],
      "parameters": [
        {
          "index": 1,
          "name": "pEntityIn"
        },
        {
          "index": 2,
          "name": "pLimbSwing"
        },
        {
          "index": 3,
          "name": "pLimbSwingAmount"
        },
        {
          "index": 4,
          "name": "pAgeInTicks"
        },
        {
          "index": 5,
          "name": "pNetHeadYaw"
        },
        {
          "index": 6,
          "name": "pHeadPitch"
        }
      ]
    },
    {
      "name": "a",
      "descriptor": "(Laqn;)V"
    },
    {
      "name": "a",
      "descriptor": "(Laqn;F)V"
    },
    {
      "name": "a",
      "descriptor": "(Laqn;FFFFF)V",
      "javadoc": [
        "Sets this entity's model rotation angles"
      ],
      "parameters": [
        {
          "index": 1,
          "name": "pEntityIn"
        },
        {
          "index": 2,
          "name": "pLimbSwing"
        },
        {
          "index": 3,
          "name": "pLimbSwingAmount"
        },
        {
          "index": 4,
          "name": "pAgeInTicks"
        },
        {
          "index": 5,
          "name": "pNetHeadYaw"
        },
        {
          "index": 6,
          "name": "pHeadPitch"
        }
      ]
    }
  ]
}