{
  "name": "eco",
  "fields": [
    {
      "name": "a",
      "descriptor": "Ljava/util/Map;"
    },
    {
      "name": "c",
      "descriptor": "Ljava/util/Map;"
    }
  ],
  "methods": [
    {
      "name": "<clinit>",
      "descriptor": "()V"
    },
    {
      "name": "<init>",
      "descriptor": "(Lecd;)V"
    },
    {
      "name": "a",
      "descriptor": "(Lbzv$a;Lcom/mojang/authlib/GameProfile;)Leao;"
    },
    {
      "name": "a",
      "descriptor": "(Lccj;FLdfm;Leag;II)V"
    },
    {
      "name": "a",
      "descriptor": "(Lcdg;FLdfm;Leag;II)V"
    },
    {
      "name": "a",
      "descriptor": "(Lgc;FLbzv$a;Lcom/mojang/authlib/GameProfile;FLdfm;Leag;I)V"
    },
    {
      "name": "a",
      "descriptor": "(Ljava/util/HashMap;)V"
    },
    {
      "name": "b",
      "descriptor": "(Ljava/util/HashMap;)V"
    }
  ]
}