{
  "name": "edt",
  "fields": [
    {
      "name": "a",
      "descriptor": "Ljava/util/List;"
    },
    {
      "name": "b",
      "descriptor": "Ljava/util/List;"
    },
    {
      "name": "c",
      "descriptor": "Ljava/util/List;"
    },
    {
      "name": "d",
      "descriptor": "Ljava/util/List;"
    },
    {
      "name": "e",
      "descriptor": "Ljava/util/List;"
    },
    {
      "name": "f",
      "descriptor": "Ljava/util/List;"
    }
  ],
  "methods": [
    {
      "name": "<init>",
      "descriptor": "()V"
    },
    {
      "name": "a",
      "descriptor": "(Ldfm;Leag;DDD)V",
      "parameters": [
        {
          "index": 1,
          "name": "pMatrixStack"
        },
        {
          "index": 2,
          "name": "pBuffer"
        },
        {
          "index": 3,
          "name": "pCamX"
        },
        {
          "index": 5,
          "name": "pCamY"
        },
        {
          "index": 7,
          "name": "pCamZ"
        }
      ]
    },
    {
      "name": "a",
      "descriptor": "(Lfx;FFFFF)V",
      "parameters": [
        {
          "index": 1,
          "name": "pPos"
        },
        {
          "index": 2,
          "name": "pSize"
        },
        {
          "index": 3,
          "name": "pRed"
        },
        {
          "index": 4,
          "name": "pGreen"
        },
        {
          "index": 5,
          "name": "pBlue"
        },
        {
          "index": 6,
          "name": "pAlpha"
        }
      ]
    }
  ]
}