{
  "name": "ej$c",
  "methods": [
    {
      "name": "<init>",
      "descriptor": "()V"
    },
    {
      "name": "a",
      "descriptor": "(Lcom/mojang/brigadier/arguments/ArgumentType;Lcom/google/gson/JsonObject;)V"
    },
    {
      "name": "a",
      "descriptor": "(Lcom/mojang/brigadier/arguments/ArgumentType;Log;)V",
      "parameters": [
        {
          "index": 1,
          "name": "pArgument"
        },
        {
          "index": 2,
          "name": "pBuffer"
        }
      ]
    },
    {
      "name": "a",
      "descriptor": "(Lej;Lcom/google/gson/JsonObject;)V"
    },
    {
      "name": "a",
      "descriptor": "(Lej;Log;)V",
      "parameters": [
        {
          "index": 1,
          "name": "pArgument"
        },
        {
          "index": 2,
          "name": "pBuffer"
        }
      ]
    },
    {
      "name": "a",
      "descriptor": "(Log;)Lej;",
      "parameters": [
        {
          "index": 1,
          "name": "pBuffer"
        }
      ]
    },
    {
      "name": "b",
      "descriptor": "(Log;)Lcom/mojang/brigadier/arguments/ArgumentType;",
      "parameters": [
        {
          "index": 1,
          "name": "pBuffer"
        }
      ]
    }
  ]
}