{
  "name": "fbr",
  "fields": [
    {
      "name": "R",
      "descriptor": "I"
    },
    {
      "name": "a",
      "descriptor": "Los;"
    },
    {
      "name": "b",
      "descriptor": "Ldxl;"
    },
    {
      "name": "c",
      "descriptor": "Leap;"
    }
  ],
  "methods": [
    {
      "name": "<init>",
      "descriptor": "(Leap;Los;Los;)V"
    },
    {
      "name": "a",
      "descriptor": "(Ldqk;IIF)V",
      "parameters": [
        {
          "index": 1,
          "name": "pMatrixStack"
        },
        {
          "index": 2,
          "name": "pMouseX"
        },
        {
          "index": 3,
          "name": "pMouseY"
        },
        {
          "index": 4,
          "name": "pPartialTicks"
        }
      ]
    },
    {
      "name": "a",
      "descriptor": "(Ldvo;Ldwz;)V"
    },
    {
      "name": "af_",
      "descriptor": "()Los;"
    },
    {
      "name": "ah_",
      "descriptor": "()V"
    },
    {
      "name": "b",
      "descriptor": "()V"
    }
  ]
}