{
  "name": "ke",
  "fields": [
    {
      "name": "a",
      "descriptor": "Lbte;"
    },
    {
      "name": "b",
      "descriptor": "Lbte;"
    },
    {
      "name": "c",
      "descriptor": "Lbql;"
    },
    {
      "name": "d",
      "descriptor": "Lae$a;"
    },
    {
      "name": "e",
      "descriptor": "Lbtj;"
    }
  ],
  "methods": [
    {
      "name": "<init>",
      "descriptor": "(Lbtj;Lbte;Lbte;Lbql;)V"
    },
    {
      "name": "a",
      "descriptor": "(Lbte;Lbte;Lbql;)Lke;"
    },
    {
      "name": "a",
      "descriptor": "(Ljava/lang/String;Lam;)Lke;"
    },
    {
      "name": "a",
      "descriptor": "(Ljava/util/function/Consumer;Ljava/lang/String;)V"
    },
    {
      "name": "a",
      "descriptor": "(Ljava/util/function/Consumer;Lww;)V"
    },
    {
      "name": "a",
      "descriptor": "(Lww;)V"
    }
  ]
}