{
  "name": "uf",
  "fields": [
    {
      "name": "a",
      "descriptor": "D"
    },
    {
      "name": "b",
      "descriptor": "D"
    },
    {
      "name": "c",
      "descriptor": "D"
    },
    {
      "name": "d",
      "descriptor": "F"
    },
    {
      "name": "e",
      "descriptor": "F"
    },
    {
      "name": "f",
      "descriptor": "Z"
    },
    {
      "name": "g",
      "descriptor": "Z"
    },
    {
      "name": "h",
      "descriptor": "Z"
    }
  ],
  "methods": [
    {
      "name": "<init>",
      "descriptor": "(DDDFFZZZ)V"
    },
    {
      "name": "a",
      "descriptor": "(D)D",
      "parameters": [
        {
          "index": 1,
          "name": "pDefaultValue"
        }
      ]
    },
    {
      "name": "a",
      "descriptor": "(F)F",
      "parameters": [
        {
          "index": 1,
          "name": "pDefaultValue"
        }
      ]
    },
    {
      "name": "a",
      "descriptor": "(Loj;)V"
    },
    {
      "name": "a",
      "descriptor": "(Ltn;)V",
      "javadoc": [
        "Passes this Packet on to the NetHandler for processing."
      ],
      "parameters": [
        {
          "index": 1,
          "name": "pHandler"
        }
      ]
    },
    {
      "name": "b",
      "descriptor": "()Z"
    },
    {
      "name": "b",
      "descriptor": "(D)D",
      "parameters": [
        {
          "index": 1,
          "name": "pDefaultValue"
        }
      ]
    },
    {
      "name": "b",
      "descriptor": "(F)F",
      "parameters": [
        {
          "index": 1,
          "name": "pDefaultValue"
        }
      ]
    },
    {
      "name": "c",
      "descriptor": "()Z"
    },
    {
      "name": "c",
      "descriptor": "(D)D",
      "parameters": [
        {
          "index": 1,
          "name": "pDefaultValue"
        }
      ]
    },
    {
      "name": "d",
      "descriptor": "()Z"
    }
  ]
}