{
  "name": "com/mojang/blaze3d/audio/Library",
  "methods": [
    {
      "name": "acquireChannel",
      "descriptor": "(Lcom/mojang/blaze3d/audio/Library$Pool;)Lcom/mojang/blaze3d/audio/Channel;",
      "javadoc": [
        "Gets the source of a sound based on the mode"
      ],
      "parameters": [
        {
          "index": 1,
          "name": "soundMode"
        }
      ]
    },
    {
      "name": "releaseChannel",
      "descriptor": "(Lcom/mojang/blaze3d/audio/Channel;)V",
      "parameters": [
        {
          "index": 1,
          "name": "source"
        }
      ]
    }
  ]
}