{
  "name": "net/minecraft/world/level/levelgen/feature/blockplacers/BlockPlacer",
  "methods": [
    {
      "name": "place",
      "descriptor": "(Lnet/minecraft/world/level/LevelAccessor;Lnet/minecraft/core/BlockPos;Lnet/minecraft/world/level/block/state/BlockState;Ljava/util/Random;)V",
      "parameters": [
        {
          "index": 1,
          "name": "level"
        },
        {
          "index": 2,
          "name": "pos"
        },
        {
          "index": 3,
          "name": "state"
        },
        {
          "index": 4,
          "name": "random"
        }
      ]
    }
  ]
}